LICENSE
README.md
easy_functions.py
setup.py
easy_functions.egg-info/PKG-INFO
easy_functions.egg-info/SOURCES.txt
easy_functions.egg-info/dependency_links.txt
easy_functions.egg-info/top_level.txt