Metadata-Version: 2.1
Name: easy-functions
Version: 4.20.91
Summary: 一个简单小巧但实用的模块
Home-page: https://github.com/MCTF-Alpha-27/easy_functions
Author: Jerry0940
Author-email: j13816180940@139.com
License: MIT
Platform: UNKNOWN
Classifier: Programming Language :: Python :: 3
License-File: LICENSE
